{
  "book_title": "Bishop Pattern Recognition and Machine Learning 2006",
  "s3_path": "books/Bishop-Pattern-Recognition-and-Machine-Learning-2006.pdf",
  "start_time": "2025-10-19T00:01:07.365259",
  "iterations": [
    {
      "iteration": 1,
      "timestamp": "2025-10-19T00:01:14.788186",
      "recommendations": {
        "critical": [],
        "important": [],
        "nice_to_have": []
      }
    },
    {
      "iteration": 2,
      "timestamp": "2025-10-19T00:01:22.667951",
      "recommendations": {
        "critical": [],
        "important": [],
        "nice_to_have": []
      }
    },
    {
      "iteration": 3,
      "timestamp": "2025-10-19T00:01:31.695691",
      "recommendations": {
        "critical": [],
        "important": [],
        "nice_to_have": []
      }
    },
    {
      "iteration": 4,
      "timestamp": "2025-10-19T00:01:38.488168",
      "recommendations": {
        "critical": [],
        "important": [],
        "nice_to_have": []
      }
    },
    {
      "iteration": 5,
      "timestamp": "2025-10-19T00:01:46.590874",
      "recommendations": {
        "critical": [],
        "important": [],
        "nice_to_have": []
      }
    },
    {
      "iteration": 6,
      "timestamp": "2025-10-19T00:01:54.204429",
      "recommendations": {
        "critical": [],
        "important": [],
        "nice_to_have": []
      }
    },
    {
      "iteration": 7,
      "timestamp": "2025-10-19T00:02:01.237500",
      "recommendations": {
        "critical": [],
        "important": [],
        "nice_to_have": []
      }
    },
    {
      "iteration": 8,
      "timestamp": "2025-10-19T00:02:08.928548",
      "recommendations": {
        "critical": [],
        "important": [],
        "nice_to_have": []
      }
    },
    {
      "iteration": 9,
      "timestamp": "2025-10-19T00:02:18.098495",
      "recommendations": {
        "critical": [],
        "important": [],
        "nice_to_have": []
      }
    },
    {
      "iteration": 10,
      "timestamp": "2025-10-19T00:02:24.865373",
      "recommendations": {
        "critical": [],
        "important": [],
        "nice_to_have": []
      }
    },
    {
      "iteration": 11,
      "timestamp": "2025-10-19T00:02:31.919920",
      "recommendations": {
        "critical": [],
        "important": [],
        "nice_to_have": []
      }
    },
    {
      "iteration": 12,
      "timestamp": "2025-10-19T00:02:38.899475",
      "recommendations": {
        "critical": [],
        "important": [],
        "nice_to_have": []
      }
    },
    {
      "iteration": 13,
      "timestamp": "2025-10-19T00:02:46.746420",
      "recommendations": {
        "critical": [],
        "important": [],
        "nice_to_have": []
      }
    },
    {
      "iteration": 14,
      "timestamp": "2025-10-19T00:02:54.669470",
      "recommendations": {
        "critical": [],
        "important": [],
        "nice_to_have": []
      }
    },
    {
      "iteration": 15,
      "timestamp": "2025-10-19T00:03:02.229600",
      "recommendations": {
        "critical": [],
        "important": [],
        "nice_to_have": []
      }
    }
  ],
  "convergence_achieved": false,
  "convergence_iteration": null,
  "total_recommendations": {
    "critical": 0,
    "important": 0,
    "nice_to_have": 0
  },
  "new_recommendations": 0,
  "duplicate_recommendations": 0,
  "improved_recommendations": 0,
  "end_time": "2025-10-19T00:03:02.229619",
  "total_iterations": 15
}