{
  "book_title": "Sports Analytics",
  "s3_path": "books/Sports_Analytics.pdf",
  "start_time": "2025-10-19T05:19:39.808803",
  "iterations": [
    {
      "iteration": 1,
      "timestamp": "2025-10-19T05:19:40.756695",
      "recommendations": {
        "critical": [],
        "important": [],
        "nice_to_have": []
      }
    },
    {
      "iteration": 2,
      "timestamp": "2025-10-19T05:19:41.411398",
      "recommendations": {
        "critical": [],
        "important": [],
        "nice_to_have": []
      }
    },
    {
      "iteration": 3,
      "timestamp": "2025-10-19T05:19:42.040688",
      "recommendations": {
        "critical": [],
        "important": [],
        "nice_to_have": []
      }
    },
    {
      "iteration": 4,
      "timestamp": "2025-10-19T05:19:42.687240",
      "recommendations": {
        "critical": [],
        "important": [],
        "nice_to_have": []
      }
    },
    {
      "iteration": 5,
      "timestamp": "2025-10-19T05:19:43.350296",
      "recommendations": {
        "critical": [],
        "important": [],
        "nice_to_have": []
      }
    },
    {
      "iteration": 6,
      "timestamp": "2025-10-19T05:19:44.004031",
      "recommendations": {
        "critical": [],
        "important": [],
        "nice_to_have": []
      }
    },
    {
      "iteration": 7,
      "timestamp": "2025-10-19T05:19:44.635368",
      "recommendations": {
        "critical": [],
        "important": [],
        "nice_to_have": []
      }
    },
    {
      "iteration": 8,
      "timestamp": "2025-10-19T05:19:45.249477",
      "recommendations": {
        "critical": [],
        "important": [],
        "nice_to_have": []
      }
    },
    {
      "iteration": 9,
      "timestamp": "2025-10-19T05:19:45.862582",
      "recommendations": {
        "critical": [],
        "important": [],
        "nice_to_have": []
      }
    },
    {
      "iteration": 10,
      "timestamp": "2025-10-19T05:19:46.494018",
      "recommendations": {
        "critical": [],
        "important": [],
        "nice_to_have": []
      }
    },
    {
      "iteration": 11,
      "timestamp": "2025-10-19T05:19:47.155223",
      "recommendations": {
        "critical": [],
        "important": [],
        "nice_to_have": []
      }
    },
    {
      "iteration": 12,
      "timestamp": "2025-10-19T05:19:47.770790",
      "recommendations": {
        "critical": [],
        "important": [],
        "nice_to_have": []
      }
    },
    {
      "iteration": 13,
      "timestamp": "2025-10-19T05:19:48.416984",
      "recommendations": {
        "critical": [],
        "important": [],
        "nice_to_have": []
      }
    },
    {
      "iteration": 14,
      "timestamp": "2025-10-19T05:19:49.042045",
      "recommendations": {
        "critical": [],
        "important": [],
        "nice_to_have": []
      }
    },
    {
      "iteration": 15,
      "timestamp": "2025-10-19T05:19:49.704336",
      "recommendations": {
        "critical": [],
        "important": [],
        "nice_to_have": []
      }
    }
  ],
  "convergence_achieved": false,
  "convergence_iteration": null,
  "total_recommendations": {
    "critical": 0,
    "important": 0,
    "nice_to_have": 0
  },
  "new_recommendations": 0,
  "duplicate_recommendations": 0,
  "improved_recommendations": 0,
  "end_time": "2025-10-19T05:19:49.704358",
  "total_iterations": 15
}